cap_alerts/__init__.py
cap_alerts/apps.py
cap_alerts/exceptions.py
cap_alerts/manager.py
cap_alerts/models.py
cap_alerts/serializers.py
cap_alerts/tasks.py
cap_alerts/utils.py
cap_alerts/engage/__init__.py
cap_alerts/engage/engage_client.py
cap_alerts/engage/engage_config.py
cap_alerts/engage/engage_exceptions.py
cap_alerts/engage/engage_models.py
cap_alerts/meteoalarm/__init__.py
cap_alerts/meteoalarm/meteoalarm_client.py
cap_alerts/meteoalarm/meteoalarm_config.py
cap_alerts/meteoalarm/meteoalarm_exceptions.py
cap_alerts/migrations/0001_initial.py
cap_alerts/migrations/__init__.py
django_cap_alerts-1.0.0.dist-info/licenses/LICENSE
django_cap_alerts-1.0.0.dist-info/METADATA
django_cap_alerts-1.0.0.dist-info/WHEEL
django_cap_alerts-1.0.0.dist-info/top_level.txt
django_cap_alerts-1.0.0.dist-info/RECORD
