Metadata-Version: 2.4
Name: django-cap-alerts
Version: 1.0.0
Summary: Django package for CAP (Common Alerting Protocol)
Home-page: https://gitlab.com/otsagketas1/cap-package
Author: Orestis Tsagketas
Author-email: Orestis Tsagketas <otsagketas@getmap.gr>
Maintainer-email: Orestis Tsagketas <otsagketas@getmap.gr>
License: MIT
Project-URL: Homepage, https://gitlab.com/otsagketas1/cap-package
Project-URL: Documentation, https://gitlab.com/otsagketas1/cap-package/-/blob/main/django_cap_alerts/README.md
Project-URL: Repository, https://gitlab.com/otsagketas1/cap-package
Project-URL: Bug Tracker, https://gitlab.com/otsagketas1/cap-package/-/issues
Project-URL: API Documentation, https://gitlab.com/otsagketas1/cap-package/-/blob/main/django_cap_alerts/docs/MANAGER_DOCS.md
Keywords: django,cap,alerts
Classifier: Development Status :: 4 - Beta
Classifier: Environment :: Web Environment
Classifier: Framework :: Django
Classifier: Framework :: Django :: 4.2
Classifier: Intended Audience :: Developers
Classifier: License :: OSI Approved :: MIT License
Classifier: Operating System :: OS Independent
Classifier: Programming Language :: Python
Classifier: Programming Language :: Python :: 3
Classifier: Programming Language :: Python :: 3.8
Classifier: Programming Language :: Python :: 3.9
Classifier: Programming Language :: Python :: 3.10
Classifier: Programming Language :: Python :: 3.11
Classifier: Topic :: Internet :: WWW/HTTP
Classifier: Topic :: Software Development :: Libraries :: Python Modules
Requires-Python: >=3.8
License-File: LICENSE
Requires-Dist: Django>=4.2.0
Requires-Dist: djangorestframework>=3.14.0
Requires-Dist: djangorestframework-gis>=1.0.0
Requires-Dist: psycopg2-binary>=2.9.0
Requires-Dist: celery>=5.3.0
Requires-Dist: redis>=5.0.0
Requires-Dist: requests>=2.31.0
Provides-Extra: dev
Requires-Dist: pytest>=7.0.0; extra == "dev"
Requires-Dist: pytest-django>=4.5.0; extra == "dev"
Requires-Dist: black>=23.0.0; extra == "dev"
Requires-Dist: flake8>=6.0.0; extra == "dev"
Requires-Dist: isort>=5.12.0; extra == "dev"
Dynamic: author
Dynamic: home-page
Dynamic: license-file
Dynamic: requires-python
